braingeneers/__init__.py
braingeneers/py.typed
braingeneers/analysis/__init__.py
braingeneers/analysis/analysis.py
braingeneers/analysis/visualize_maxwell.py
braingeneers/data/__init__.py
braingeneers/data/datasets_electrophysiology.py
braingeneers/data/datasets_fluidics.py
braingeneers/data/datasets_imaging.py
braingeneers/data/datasets_neuron.py
braingeneers/data/mxw_h5_plugin/Linux/libcompression.so
braingeneers/data/mxw_h5_plugin/Mac_arm64/libcompression.dylib
braingeneers/data/mxw_h5_plugin/Mac_x86_64/libcompression.dylib
braingeneers/data/mxw_h5_plugin/Windows/compression.dll
braingeneers/data/transforms/__init__.py
braingeneers/iot/__init__.py
braingeneers/iot/authenticate.py
braingeneers/iot/device.py
braingeneers/iot/example_device.py
braingeneers/iot/example_device_main.py
braingeneers/iot/gui.py
braingeneers/iot/messaging.py
braingeneers/iot/shadows.py
braingeneers/iot/shadows_dev_playground.py
braingeneers/iot/simple.py
braingeneers/ml/__init__.py
braingeneers/ml/ephys_dataloader.py
braingeneers/utils/__init__.py
braingeneers/utils/common_utils.py
braingeneers/utils/configure.py
braingeneers/utils/memoize_s3.py
braingeneers/utils/numpy_s3_memmap.py
braingeneers/utils/s3wrangler/__init__.py
braingeneers/utils/smart_open_braingeneers/__init__.py
braingeneers-0.3.1.10.dist-info/METADATA
braingeneers-0.3.1.10.dist-info/WHEEL
braingeneers-0.3.1.10.dist-info/licenses/LICENSE
braingeneers-0.3.1.10.dist-info/RECORD
