Metadata-Version: 2.4
Name: braingeneers
Version: 0.3.1.10
Summary: Braingeneers Python utilities
Project-URL: Homepage, https://github.com/braingeneers/braingeneerspy
Project-URL: Bug Tracker, https://github.com/braingeneers/braingeneerspy/issues
Project-URL: Discussions, https://github.com/braingeneers/braingeneerspy/discussions
Project-URL: Changelog, https://github.com/braingeneers/braingeneerspy/releases
Author-email: UCSC Braingeneers <braingeneers-admins-group@ucsc.edu>
Maintainer-email: David Parks <dfparks@ucsc.edu>, Kate Voitiuk <kvoitiuk@ucsc.edu>
License-File: LICENSE
Classifier: Development Status :: 3 - Alpha
Classifier: Intended Audience :: Developers
Classifier: Intended Audience :: Science/Research
Classifier: License :: OSI Approved :: MIT License
Classifier: Operating System :: OS Independent
Classifier: Programming Language :: Python
Classifier: Programming Language :: Python :: 3
Classifier: Programming Language :: Python :: 3 :: Only
Classifier: Programming Language :: Python :: 3.10
Classifier: Programming Language :: Python :: 3.11
Classifier: Topic :: Scientific/Engineering
Classifier: Typing :: Typed
Requires-Python: >=3.10
Requires-Dist: awswrangler==3.*
Requires-Dist: boto3==1.35.95
Requires-Dist: braingeneers-smart-open==2023.10.6
Requires-Dist: deprecated
Requires-Dist: diskcache
Requires-Dist: h5py
Requires-Dist: matplotlib
Requires-Dist: nptyping
Requires-Dist: numpy
Requires-Dist: paho-mqtt>=2
Requires-Dist: pandas
Requires-Dist: pytz
Requires-Dist: redis
Requires-Dist: requests
Requires-Dist: schedule
Requires-Dist: scipy
Requires-Dist: spikedata
Requires-Dist: tenacity
Requires-Dist: typing-extensions>=4.6; python_version < '3.11'
Requires-Dist: tzlocal
Provides-Extra: all
Requires-Dist: furo; extra == 'all'
Requires-Dist: joblib; extra == 'all'
Requires-Dist: myst-parser>=0.13; extra == 'all'
Requires-Dist: pytest-cov>=3; extra == 'all'
Requires-Dist: pytest>=6; extra == 'all'
Requires-Dist: scikit-learn; extra == 'all'
Requires-Dist: sphinx-autodoc-typehints; extra == 'all'
Requires-Dist: sphinx-book-theme>=0.1.0; extra == 'all'
Requires-Dist: sphinx-copybutton; extra == 'all'
Requires-Dist: sphinx>=4.0; extra == 'all'
Requires-Dist: torch; extra == 'all'
Provides-Extra: dev
Requires-Dist: furo; extra == 'dev'
Requires-Dist: joblib; extra == 'dev'
Requires-Dist: myst-parser>=0.13; extra == 'dev'
Requires-Dist: pytest-cov>=3; extra == 'dev'
Requires-Dist: pytest>=6; extra == 'dev'
Requires-Dist: sphinx-autodoc-typehints; extra == 'dev'
Requires-Dist: sphinx-book-theme>=0.1.0; extra == 'dev'
Requires-Dist: sphinx-copybutton; extra == 'dev'
Requires-Dist: sphinx>=4.0; extra == 'dev'
Provides-Extra: ml
Requires-Dist: scikit-learn; extra == 'ml'
Requires-Dist: torch; extra == 'ml'
